nmdc_mongo/__init__.py
nmdc_mongo/admin.py
nmdc_mongo_tools-0.0.7.dist-info/LICENSE
nmdc_mongo_tools-0.0.7.dist-info/METADATA
nmdc_mongo_tools-0.0.7.dist-info/WHEEL
nmdc_mongo_tools-0.0.7.dist-info/top_level.txt
nmdc_mongo_tools-0.0.7.dist-info/RECORD
