Metadata-Version: 2.1
Name: nmdc-mongo-tools
Version: 0.0.7
Summary: Tools for validation and storage of JSON data using the NMDC Schema
Home-page: https://github.com/polyneme/nmdc-mongo-tools
Author: Donny Winston
Author-email: donny@polyneme.xyz
License: UNKNOWN
Platform: UNKNOWN
Classifier: Development Status :: 3 - Alpha
Classifier: Programming Language :: Python :: 3
Classifier: License :: OSI Approved :: Apache Software License
Requires-Python: >=3.6
Requires-Dist: jsonschema
Requires-Dist: mongospawn
Requires-Dist: pymongo
Requires-Dist: python-dotenv
Requires-Dist: requests
Requires-Dist: tqdm
Requires-Dist: toolz
Provides-Extra: dev
Requires-Dist: black ; extra == 'dev'
Requires-Dist: invoke ; extra == 'dev'
Requires-Dist: pytest ; extra == 'dev'
Requires-Dist: setuptools-scm ; extra == 'dev'
Requires-Dist: twine ; extra == 'dev'
